dualSevenSeg.v
module dualSevenSeg(data1,data2,display2,display1);
//this module will print to two 7-segment display's at the same time.
input [3:0]data1;
input [3:0]data2;
output [7:0] display1;
output [7:0] display2;
reg [7:0]display1;
reg [7:0]display2;

always @* //right-most digit, display1
begin
    casex (data1[3:0])
        4'b0000 : display1 = 8'b11000000; //0
        4'b0001 : display1 = 8'b11111001; //1
        4'b0010 : display1 = 8'b10100100; //2
        4'b0011 : display1 = 8'b10110000; //3
        4'b0100 : display1 = 8'b10011001; //4
        4'b0101 : display1 = 8'b10010010; //5
        4'b0110 : display1 = 8'b10000010; //6
        4'b0111 : display1 = 8'b11111000; //7
        4'b1000 : display1 = 8'b10000000; //8
        4'b1001 : display1 = 8'b10010000; //9
    endcase
end
always @*
begin
    casex (data2[3:0])
        4'b0000 : display2 = 8'b11111111; //blank
        4'b0001 : display2 = 8'b11111001; //1
        4'b0010 : display2 = 8'b10100100; //2
        4'b0011 : display2 = 8'b10110000; //3
        4'b0100 : display2 = 8'b10011001; //4
        4'b0101 : display2 = 8'b10010010; //5
        4'b0110 : display2 = 8'b10000010; //6
        4'b0111 : display2 = 8'b11111000; //7
        4'b1000 : display2 = 8'b10000000; //8
        4'b1001 : display2 = 8'b10010000; //9
    endcase
end
endmodule

counted.v
module counted(count, left, right);
input [6:0]count;
output [3:0]right;
output [3:0]left;
reg [3:0]left;
reg [3:0]right;
always @*
begin
right = (count %10);
left = (count /10);
end
endmodule

monthDayCalc.v
module monthDayCalc(data,month,day1,day2,SmoW);
//input number of the day of the year, outputs the month and day
// day1 is leftmost 7-seg (Overflow bit) , day2 is rightmost 7-seg
input [6:0] data;
output [7:0] month;//count
output [3:0] day1;//mod1
output [3:0] day2;//mod2
reg [7:0] dayData;//should be 7:0 not six 8 bit total
reg [7:0] month;
reg [3:0] day1;
reg [3:0] day2;


input [9:8]SW;


always @* //sending out month 7-segment binary value
begin
if(SW[9] == 1'b1)//leap year
begin
   if(data>=7'd92)  
    month = 8'b10011001; //4 - April
   else if(data>=7'd61)  
    month = 8'b10110000; //3 - March
   else if(data>=7'd32)
    month = 8'b10100100; //2 - February
   else
    month = 8'b11111001; //1 - January
end
else 
begin
   if(data>=7'd91)  
    month = 8'b10011001; //4 - April
   else if(data>=7'd60)  
    month = 8'b10110000; //3 - March
   else if(data>=7'd32)
    month = 8'b10100100; //2 - February
   else
    month = 8'b11111001; //1 - January
end
end

always @* //Get the date of the month
begin
if(SW[9] == 1'b1)
begin
   if(data>=7'd92)  
    dayData = (data % 7'd91); //4 - Aprl
   else if(data>=7'd61)  
    dayData = (data % 7'd60); //3 - March
   else if(data>=7'd32)
    dayData = (data % 7'd31); //2 - February
   else
    dayData = data;         //1 - January
end
else
begin
   if(data>=7'd91)  
    dayData = (data % 7'd90); //4 - Aprl
   else if(data>=7'd60)  
    dayData = (data % 7'd59); //3 - March
   else if(data>=7'd32)
    dayData = (data % 7'd31); //2 - February
   else
    dayData = data;         //1 - January
end
end

always @*
begin
    day2 = (dayData%10); //rightmost bit
    day1 = (dayData/10); //overflow left bit
end


endmodule

clock_divider.v
module clock_divider (clk, /*reset_n,*/clock_out, KEY, clock_divisor1,clock_divisor2);
//parameter clock_divisor = 5_000_000; //move to top in test pass 1
input [1:0]KEY;
input clk;
input [31:0]clock_divisor1;
input [31:0]clock_divisor2;
//input [0]reset_n;
//input [0]clock_divider; //TB = 1 TOP = 5_000_000
output clock_out;
reg clock_out = 0;
reg [23:0]counter = 0;


//(clock_divider #(clock_divisor = 1); //look up parameter verilog
always @(posedge clk)
begin
    /*if(KEY[0] == 1'b0)
    begin
        counter = 0;
        clock_out = 0;
    end*/
    if(KEY[1] == 1'b1)
    begin
        if(counter == clock_divisor1 - 1)
        begin
            counter <= 0;
            clock_out <= ~clock_out;
        end
        else
            counter <= counter + 1;
    end
    else
    begin
        if(counter == clock_divisor2 - 1)
        begin
            counter <= 0;
            clock_out <= ~clock_out;
        end
        else
            counter <= counter + 1;
    end
end


endmodule
/*
reg [6:0]count;
reg [3:0]mod10_counter1;
reg [3:0]mod10_counter2;
always @(posedge clk or negedge reset_n)
begin
if(reset_n == 0)
begin
mod10_counter1 <= 1; // start at 1
count <= 1; //count 1 - 99
end
else if (mod10_counter1 != 9)
begin
mod10_counter <= mod10_counter + 1;
count <= count + 1;
end
else if(count == 99)
mod10_counter1 <= 0;
else
begin
mod10_counter <= 0;
count <= count + 1;
end
end

always @(posedge clk or negedge reset_n)
begin
if(reset_n == 0)
mod10_counter2 <= 0;
else if(mod10_counter1 == 9)
begin
if (mod10_counter2 != 9)
mod10_counter2 <= mod10_counter2 + 1;
else
mod10_counter2 <= 0;
end
end


endmodule

module top(ADC_CLK_10)
input ADC_CLK_10;
*/

top.v
module top #(parameter clock_divisor1 = 1, parameter clock_divisor2 = 1_000_000) (KEY, HEX0, HEX1, HEX2, HEX3, HEX4, HEX5, ADC_CLK_10, LEDR, SW);
//clock input
input ADC_CLK_10;

//set input for KEY buttons
input [1:0] KEY; 
input [9:8] SW;
//Outputs need wires here because through the 3 blocks each hex holds 3 different values
output [7:0] HEX0; //Day2
output [7:0] HEX1; //Day1
output [7:0] HEX2; //Month 
output [7:0] HEX3; //Blank
output [7:0] HEX4; //Digit 2
output [7:0] HEX5; //Digit 1
output [1:0] LEDR;

assign HEX3[7:0] = 8'b11111111; // Make HEX3 blank
//count   
wire[3:0]day1; //This is the HEX1 number representation
wire[3:0]day2; //This is the HEX0 number representation
wire[3:0]right;
wire[3:0]left;
wire [7:0]monthSeg; //7-seg display binary represntation for the month, HEX2
reg [1:0]LEDR = 2'b01;

//Latch the button
reg reset_n = 0;
always @(negedge KEY[0])
begin
    reset_n <= ~reset_n;
    LEDR[0] = reset_n;
end


wire clk_out;
clock_divider clock_divide(.clk(ADC_CLK_10),.clock_out(clk_out), .KEY(KEY[1:0]),.clock_divisor1(clock_divisor1),.clock_divisor2(clock_divisor2));

//Start Clock setup
reg [6:0]count = 0;
reg [3:0]mod10_counter1 = 0;
reg [3:0]mod10_counter2 = 0;
//Day1
always @(posedge clk_out or negedge reset_n)
begin
    if(reset_n == 0)
    begin
        mod10_counter1 <= 1; // start at 1
        count <= 1; //count 1 - 99
    end
    else 
    begin
        LEDR[1] <= ~LEDR[1];
        if(count == 99)
        begin
        mod10_counter1 <= 1;
        count <= 1;
        end
        else 
        if (mod10_counter1 != 9)
        begin
            mod10_counter1 <= mod10_counter1 + 1;
            count <= count + 1;
        end
        else
        begin
            mod10_counter1 <= 0;
            count <= count + 1;
        end
    end
end
//Day2
always @(posedge clk_out or negedge reset_n)
begin
    if(reset_n == 0)
        mod10_counter2 <= 0;
    else if(mod10_counter1 == 9)
    begin
        if (/*mod10_counter2*/count != 100)
            mod10_counter2 <= mod10_counter2 + 1;
        else
        begin
            mod10_counter2 <= 0;
            //count = 1;
        end
    end
end
// end clock setup

// printing to 7-segment displays
monthDayCalc monthDayCalc(.data(count),.month(HEX2),.day1(day1),.day2(day2),.SW(SW[9:8]));
dualSevenSeg dualSevenSegMD(.data1(day2),.data2(day1),.display2(HEX1),.display1(HEX0));
counted counted(.count(count),.left(left),.right(right));
dualSevenSeg dualSevenSegCNT(.data1(right),.data2(left),.display2(HEX5),.display1(HEX4));



endmodule

tb_project2.v
/* USE:
 ~from directory project2digitallogic/
 ~iverilog tb_project2.v top.v monthDayCalc.v dualSevenSeg.v clock_divider.v counted.v
 ~vvp a.out > out.txt
 */
`timescale 1 s / 100 ns

module tb();

reg ADC_CLK_10;
reg  [9:8] SW;
reg  [1:0] KEY; //Buttons
wire [7:0] HEX0; //Day2
wire [7:0] HEX1; //Day1
wire [7:0] HEX2; //Month
wire [7:0] HEX3; //should always be blank
wire [7:0] HEX4; //Digit 1
wire [7:0] HEX5; //Digit 2
wire [1:0] LEDR;

reg [3:0] day1digit;
reg [3:0] day2digit;
reg [3:0] monthDigit;
reg [3:0] unusedMonthDig;
reg [3:0] digit1digit;
reg [3:0] digit2digit;

always #1 ADC_CLK_10 = ~ADC_CLK_10;

top #(1,2) DUT(
  .KEY(KEY),
  .HEX0(HEX0),
  .HEX1(HEX1),
  .HEX2(HEX2),
  .HEX3(HEX3),
  .HEX4(HEX4),
  .HEX5(HEX5),
  .ADC_CLK_10(ADC_CLK_10),
  .LEDR(LEDR),
  .SW(SW)  
);

initial
begin
    $dumpfile("out.vcd");
	$dumpvars;
    $display($time, " << Starting Simulation >>");
    ADC_CLK_10 = 1'b0;
    SW[9:8] = 2'b00;
    KEY[1:0] = 2'b11;
    $display($time, " SW[9] low: %b, no buttons KEY[1:0]= %b",SW[9],KEY[1:0]);
    #1
    KEY[1:0] = 2'b10;
    #1
    $display($time, " Pressing reset to begin, KEY[0] = %b, HEX3 Cleared: %b",KEY[0],HEX3[7:0]);
    repeat(100) begin
        if($time<3) KEY[1:0] = 2'b11;
        #1
        $display($time, " Left Digit: HEX5 = %b, Right Digit: HEX4 = %b", HEX5[7:0], HEX4[7:0]);
        $display($time, " Left Day: HEX1 = %b, Right Day: HEX0 = %b, Month: HEX2 = %b",HEX1[7:0],HEX0[7:0],HEX2[7:0]);
        $display($time," Converted to digits: %d %d - %d %d - %d %d",
                   digit2digit[3:0],digit1digit[3:0],unusedMonthDig[3:0], monthDigit[3:0],day1digit[3:0],day2digit[3:0]);
    end
    
    $display($time, " Ending Simulation, by Connor Peskin");
	$finish;
end

initial
begin
      $monitor($time, " Buttons(KEY): %b, Day2(HEX0): %b, Day1(HEX1): %b, UnusedMonth(HEX3): %b, Month(HEX2): %b, Digit1(HEX4): %b, Digit2(HEX5): %b, Clk: %b",
                              KEY[1:0],      HEX0[7:0],      HEX1[7:0],               HEX3[7:0], HEX2[7:0],        HEX4[7:0],        HEX5[7:0], ADC_CLK_10);
end


always @* 
begin
    casex(HEX1[7:0])
        8'b11111111 : day1digit = 4'b0000; //0
        8'b11111001 : day1digit = 4'b0001; //1
        8'b10100100 : day1digit = 4'b0010; //2
        8'b10110000 : day1digit = 4'b0011; //3
        8'b10011001 : day1digit = 4'b0100; //4
        8'b10010010 : day1digit = 4'b0101; //5
        8'b10000010 : day1digit = 4'b0110; //6
        8'b11111000 : day1digit = 4'b0111; //7
        8'b10000000 : day1digit = 4'b1000; //8
        8'b10010000 : day1digit = 4'b1001; //9
    endcase
    casex(HEX0[7:0])
        8'b11000000 : day2digit = 4'b0000; //0
        8'b11111001 : day2digit = 4'b0001; //1
        8'b10100100 : day2digit = 4'b0010; //2
        8'b10110000 : day2digit = 4'b0011; //3
        8'b10011001 : day2digit = 4'b0100; //4
        8'b10010010 : day2digit = 4'b0101; //5
        8'b10000010 : day2digit = 4'b0110; //6
        8'b11111000 : day2digit = 4'b0111; //7
        8'b10000000 : day2digit = 4'b1000; //8
        8'b10010000 : day2digit = 4'b1001; //9
    endcase
    casex(HEX2[7:0])
        8'b11000000 : monthDigit = 4'b0000; //0
        8'b11111001 : monthDigit = 4'b0001; //1
        8'b10100100 : monthDigit = 4'b0010; //2
        8'b10110000 : monthDigit = 4'b0011; //3
        8'b10011001 : monthDigit = 4'b0100; //4
        8'b10010010 : monthDigit = 4'b0101; //5
        8'b10000010 : monthDigit = 4'b0110; //6
        8'b11111000 : monthDigit = 4'b0111; //7
        8'b10000000 : monthDigit = 4'b1000; //8
        8'b10010000 : monthDigit = 4'b1001; //9
    endcase
    casex(HEX3[7:0])
        8'b11000000 : unusedMonthDig = 4'b0000; //0
        8'b11111001 : unusedMonthDig = 4'b0001; //1
        8'b10100100 : unusedMonthDig = 4'b0010; //2
        8'b10110000 : unusedMonthDig = 4'b0011; //3
        8'b10011001 : unusedMonthDig = 4'b0100; //4
        8'b10010010 : unusedMonthDig = 4'b0101; //5
        8'b10000010 : unusedMonthDig = 4'b0110; //6
        8'b11111000 : unusedMonthDig = 4'b0111; //7
        8'b10000000 : unusedMonthDig = 4'b1000; //8
        8'b10010000 : unusedMonthDig = 4'b1001; //9
        8'b11111111 : unusedMonthDig = 4'b0000; //0
    endcase
    casex(HEX4[7:0])
        8'b11111111 : digit1digit = 4'b0000; //0
        8'b11111001 : digit1digit = 4'b0001; //1
        8'b10100100 : digit1digit = 4'b0010; //2
        8'b10110000 : digit1digit = 4'b0011; //3
        8'b10011001 : digit1digit = 4'b0100; //4
        8'b10010010 : digit1digit = 4'b0101; //5
        8'b10000010 : digit1digit = 4'b0110; //6
        8'b11111000 : digit1digit = 4'b0111; //7
        8'b10000000 : digit1digit = 4'b1000; //8
        8'b10010000 : digit1digit = 4'b1001; //9
    endcase
    casex(HEX5[7:0])
        8'b11000000 : digit2digit = 4'b0000; //0
        8'b11111001 : digit2digit = 4'b0001; //1
        8'b10100100 : digit2digit = 4'b0010; //2
        8'b10110000 : digit2digit = 4'b0011; //3
        8'b10011001 : digit2digit = 4'b0100; //4
        8'b10010010 : digit2digit = 4'b0101; //5
        8'b10000010 : digit2digit = 4'b0110; //6
        8'b11111000 : digit2digit = 4'b0111; //7
        8'b10000000 : digit2digit = 4'b1000; //8
        8'b10010000 : digit2digit = 4'b1001; //9
    endcase
end



endmodule

out.vcd
$date
	Mon Nov 04 17:30:43 2019
$end
$version
	Icarus Verilog
$end
$timescale
	100ns
$end
$scope module tb $end
$var wire 8 ! HEX3 [7:0] $end
$var wire 2 " LEDR [1:0] $end
$var wire 8 # HEX5 [7:0] $end
$var wire 8 $ HEX4 [7:0] $end
$var wire 8 % HEX2 [7:0] $end
$var wire 8 & HEX1 [7:0] $end
$var wire 8 ' HEX0 [7:0] $end
$var reg 1 ( ADC_CLK_10 $end
$var reg 2 ) KEY [1:0] $end
$var reg 2 * SW [9:8] $end
$var reg 4 + day1digit [3:0] $end
$var reg 4 , day2digit [3:0] $end
$var reg 4 - digit1digit [3:0] $end
$var reg 4 . digit2digit [3:0] $end
$var reg 4 / monthDigit [3:0] $end
$var reg 4 0 unusedMonthDig [3:0] $end
$scope module DUT $end
$var wire 1 ( ADC_CLK_10 $end
$var wire 8 1 HEX3 [7:0] $end
$var wire 2 2 KEY [1:0] $end
$var wire 2 3 SW [9:8] $end
$var wire 4 4 right [3:0] $end
$var wire 4 5 left [3:0] $end
$var wire 4 6 day2 [3:0] $end
$var wire 4 7 day1 [3:0] $end
$var wire 1 8 clk_out $end
$var wire 8 9 HEX5 [7:0] $end
$var wire 8 : HEX4 [7:0] $end
$var wire 8 ; HEX2 [7:0] $end
$var wire 8 < HEX1 [7:0] $end
$var wire 8 = HEX0 [7:0] $end
$var reg 2 > LEDR [1:0] $end
$var reg 7 ? count [6:0] $end
$var reg 4 @ mod10_counter1 [3:0] $end
$var reg 4 A mod10_counter2 [3:0] $end
$var reg 1 B reset_n $end
$scope module clock_divide $end
$var wire 2 C KEY [1:0] $end
$var wire 1 ( clk $end
$var wire 32 D clock_divisor1 [31:0] $end
$var wire 32 E clock_divisor2 [31:0] $end
$var reg 1 8 clock_out $end
$var reg 24 F counter [23:0] $end
$upscope $end
$scope module counted $end
$var wire 7 G count [6:0] $end
$var reg 4 H left [3:0] $end
$var reg 4 I right [3:0] $end
$upscope $end
$scope module dualSevenSegCNT $end
$var wire 4 J data1 [3:0] $end
$var wire 4 K data2 [3:0] $end
$var reg 8 L display1 [7:0] $end
$var reg 8 M display2 [7:0] $end
$upscope $end
$scope module dualSevenSegMD $end
$var wire 4 N data2 [3:0] $end
$var wire 4 O data1 [3:0] $end
$var reg 8 P display1 [7:0] $end
$var reg 8 Q display2 [7:0] $end
$upscope $end
$scope module monthDayCalc $end
$var wire 2 R SW [9:8] $end
$var wire 7 S data [6:0] $end
$var reg 4 T day1 [3:0] $end
$var reg 4 U day2 [3:0] $end
$var reg 8 V dayData [7:0] $end
$var reg 8 W month [7:0] $end
$upscope $end
$upscope $end
$upscope $end
$enddefinitions $end
#0
$dumpvars
b11111001 W
b0 V
b0 U
b0 T
b0 S
b0 R
b11111111 Q
b11000000 P
b0 O
b0 N
b11111111 M
b11000000 L
b0 K
b0 J
b0 I
b0 H
b0 G
b0 F
b10 E
b1 D
b11 C
0B
b0 A
b0 @
b0 ?
b1 >
b11000000 =
b11111111 <
b11111001 ;
b11000000 :
b11111111 9
08
b0 7
b0 6
b0 5
b0 4
b0 3
b11 2
b11111111 1
b0 0
b1 /
b0 .
b0 -
b0 ,
b0 +
b0 *
b11 )
0(
b11000000 '
b11111111 &
b11111001 %
b11000000 $
b11111111 #
b1 "
b11111111 !
$end
#10000000
b1 -
b1 ,
b11111001 '
b11111001 =
b11111001 P
b11111001 $
b11111001 :
b11111001 L
b1 6
b1 O
b1 U
b1 4
b1 I
b1 J
b1 V
b1 ?
b1 G
b1 S
b1 @
1B
18
b10 "
b10 >
b10 )
b10 2
b10 C
1(
#20000000
b11 )
b11 2
b11 C
0(
#30000000
08
1(
#40000000
0(
#50000000
b10 -
b10 ,
b10100100 '
b10100100 =
b10100100 P
b10100100 $
b10100100 :
b10100100 L
b10 6
b10 O
b10 U
b10 4
b10 I
b10 J
b10 V
b10 ?
b10 G
b10 S
b10 @
b0 "
b0 >
18
1(
#60000000
0(
#70000000
08
1(
#80000000
0(
#90000000
b11 -
b11 ,
b10110000 '
b10110000 =
b10110000 P
b10110000 $
b10110000 :
b10110000 L
b11 6
b11 O
b11 U
b11 4
b11 I
b11 J
b11 V
b11 ?
b11 G
b11 S
b11 @
b10 "
b10 >
18
1(
#100000000
0(
#110000000
08
1(
#120000000
0(
#130000000
b100 -
b100 ,
b10011001 '
b10011001 =
b10011001 P
b10011001 $
b10011001 :
b10011001 L
b100 6
b100 O
b100 U
b100 4
b100 I
b100 J
b100 V
b100 ?
b100 G
b100 S
b100 @
b0 "
b0 >
18
1(
#140000000
0(
#150000000
08
1(
#160000000
0(
#170000000
b101 -
b101 ,
b10010010 '
b10010010 =
b10010010 P
b10010010 $
b10010010 :
b10010010 L
b101 6
b101 O
b101 U
b101 4
b101 I
b101 J
b101 V
b101 ?
b101 G
b101 S
b101 @
b10 "
b10 >
18
1(
#180000000
0(
#190000000
08
1(
#200000000
0(
#210000000
b110 -
b110 ,
b10000010 '
b10000010 =
b10000010 P
b10000010 $
b10000010 :
b10000010 L
b110 6
b110 O
b110 U
b110 4
b110 I
b110 J
b110 V
b110 ?
b110 G
b110 S
b110 @
b0 "
b0 >
18
1(
#220000000
0(
#230000000
08
1(
#240000000
0(
#250000000
b111 -
b111 ,
b11111000 '
b11111000 =
b11111000 P
b11111000 $
b11111000 :
b11111000 L
b111 6
b111 O
b111 U
b111 4
b111 I
b111 J
b111 V
b111 ?
b111 G
b111 S
b111 @
b10 "
b10 >
18
1(
#260000000
0(
#270000000
08
1(
#280000000
0(
#290000000
b1000 -
b1000 ,
b10000000 '
b10000000 =
b10000000 P
b10000000 $
b10000000 :
b10000000 L
b1000 6
b1000 O
b1000 U
b1000 4
b1000 I
b1000 J
b1000 V
b1000 ?
b1000 G
b1000 S
b1000 @
b0 "
b0 >
18
1(
#300000000
0(
#310000000
08
1(
#320000000
0(
#330000000
b1001 -
b1001 ,
b10010000 '
b10010000 =
b10010000 P
b10010000 $
b10010000 :
b10010000 L
b1001 6
b1001 O
b1001 U
b1001 4
b1001 I
b1001 J
b1001 V
b1001 ?
b1001 G
b1001 S
b1001 @
b10 "
b10 >
18
1(
#340000000
0(
#350000000
08
1(
#360000000
0(
#370000000
b1 .
b0 ,
b1 +
b11111001 &
b11111001 <
b11111001 Q
b11000000 '
b11000000 =
b11000000 P
b11111001 #
b11111001 9
b11111001 M
b11000000 $
b11000000 :
b11000000 L
b1 7
b1 N
b1 T
b0 6
b0 O
b0 U
b1 5
b1 H
b1 K
b0 4
b0 I
b0 J
b1010 V
b1 A
b1010 ?
b1010 G
b1010 S
b0 @
b0 "
b0 >
18
1(
#380000000
0(
#390000000
08
1(
#400000000
0(
#410000000
b1 -
b1 ,
b11111001 '
b11111001 =
b11111001 P
b11111001 $
b11111001 :
b11111001 L
b1 6
b1 O
b1 U
b1 4
b1 I
b1 J
b1011 V
b1011 ?
b1011 G
b1011 S
b1 @
b10 "
b10 >
18
1(
#420000000
0(
#430000000
08
1(
#440000000
0(
#450000000
b10 -
b10 ,
b10100100 '
b10100100 =
b10100100 P
b10100100 $
b10100100 :
b10100100 L
b10 6
b10 O
b10 U
b10 4
b10 I
b10 J
b1100 V
b1100 ?
b1100 G
b1100 S
b10 @
b0 "
b0 >
18
1(
#460000000
0(
#470000000
08
1(
#480000000
0(
#490000000
b11 -
b11 ,
b10110000 '
b10110000 =
b10110000 P
b10110000 $
b10110000 :
b10110000 L
b11 6
b11 O
b11 U
b11 4
b11 I
b11 J
b1101 V
b1101 ?
b1101 G
b1101 S
b11 @
b10 "
b10 >
18
1(
#500000000
0(
#510000000
08
1(
#520000000
0(
#530000000
b100 -
b100 ,
b10011001 '
b10011001 =
b10011001 P
b10011001 $
b10011001 :
b10011001 L
b100 6
b100 O
b100 U
b100 4
b100 I
b100 J
b1110 V
b1110 ?
b1110 G
b1110 S
b100 @
b0 "
b0 >
18
1(
#540000000
0(
#550000000
08
1(
#560000000
0(
#570000000
b101 -
b101 ,
b10010010 '
b10010010 =
b10010010 P
b10010010 $
b10010010 :
b10010010 L
b101 6
b101 O
b101 U
b101 4
b101 I
b101 J
b1111 V
b1111 ?
b1111 G
b1111 S
b101 @
b10 "
b10 >
18
1(
#580000000
0(
#590000000
08
1(
#600000000
0(
#610000000
b110 -
b110 ,
b10000010 '
b10000010 =
b10000010 P
b10000010 $
b10000010 :
b10000010 L
b110 6
b110 O
b110 U
b110 4
b110 I
b110 J
b10000 V
b10000 ?
b10000 G
b10000 S
b110 @
b0 "
b0 >
18
1(
#620000000
0(
#630000000
08
1(
#640000000
0(
#650000000
b111 -
b111 ,
b11111000 '
b11111000 =
b11111000 P
b11111000 $
b11111000 :
b11111000 L
b111 6
b111 O
b111 U
b111 4
b111 I
b111 J
b10001 V
b10001 ?
b10001 G
b10001 S
b111 @
b10 "
b10 >
18
1(
#660000000
0(
#670000000
08
1(
#680000000
0(
#690000000
b1000 -
b1000 ,
b10000000 '
b10000000 =
b10000000 P
b10000000 $
b10000000 :
b10000000 L
b1000 6
b1000 O
b1000 U
b1000 4
b1000 I
b1000 J
b10010 V
b10010 ?
b10010 G
b10010 S
b1000 @
b0 "
b0 >
18
1(
#700000000
0(
#710000000
08
1(
#720000000
0(
#730000000
b1001 -
b1001 ,
b10010000 '
b10010000 =
b10010000 P
b10010000 $
b10010000 :
b10010000 L
b1001 6
b1001 O
b1001 U
b1001 4
b1001 I
b1001 J
b10011 V
b10011 ?
b10011 G
b10011 S
b1001 @
b10 "
b10 >
18
1(
#740000000
0(
#750000000
08
1(
#760000000
0(
#770000000
b10 .
b0 ,
b10 +
b10100100 &
b10100100 <
b10100100 Q
b11000000 '
b11000000 =
b11000000 P
b10100100 #
b10100100 9
b10100100 M
b11000000 $
b11000000 :
b11000000 L
b10 7
b10 N
b10 T
b0 6
b0 O
b0 U
b10 5
b10 H
b10 K
b0 4
b0 I
b0 J
b10100 V
b10 A
b10100 ?
b10100 G
b10100 S
b0 @
b0 "
b0 >
18
1(
#780000000
0(
#790000000
08
1(
#800000000
0(
#810000000
b1 -
b1 ,
b11111001 '
b11111001 =
b11111001 P
b11111001 $
b11111001 :
b11111001 L
b1 6
b1 O
b1 U
b1 4
b1 I
b1 J
b10101 V
b10101 ?
b10101 G
b10101 S
b1 @
b10 "
b10 >
18
1(
#820000000
0(
#830000000
08
1(
#840000000
0(
#850000000
b10 -
b10 ,
b10100100 '
b10100100 =
b10100100 P
b10100100 $
b10100100 :
b10100100 L
b10 6
b10 O
b10 U
b10 4
b10 I
b10 J
b10110 V
b10110 ?
b10110 G
b10110 S
b10 @
b0 "
b0 >
18
1(
#860000000
0(
#870000000
08
1(
#880000000
0(
#890000000
b11 -
b11 ,
b10110000 '
b10110000 =
b10110000 P
b10110000 $
b10110000 :
b10110000 L
b11 6
b11 O
b11 U
b11 4
b11 I
b11 J
b10111 V
b10111 ?
b10111 G
b10111 S
b11 @
b10 "
b10 >
18
1(
#900000000
0(
#910000000
08
1(
#920000000
0(
#930000000
b100 -
b100 ,
b10011001 '
b10011001 =
b10011001 P
b10011001 $
b10011001 :
b10011001 L
b100 6
b100 O
b100 U
b100 4
b100 I
b100 J
b11000 V
b11000 ?
b11000 G
b11000 S
b100 @
b0 "
b0 >
18
1(
#940000000
0(
#950000000
08
1(
#960000000
0(
#970000000
b101 -
b101 ,
b10010010 '
b10010010 =
b10010010 P
b10010010 $
b10010010 :
b10010010 L
b101 6
b101 O
b101 U
b101 4
b101 I
b101 J
b11001 V
b11001 ?
b11001 G
b11001 S
b101 @
b10 "
b10 >
18
1(
#980000000
0(
#990000000
08
1(
#1000000000
0(
#1010000000
b110 -
b110 ,
b10000010 '
b10000010 =
b10000010 P
b10000010 $
b10000010 :
b10000010 L
b110 6
b110 O
b110 U
b110 4
b110 I
b110 J
b11010 V
b11010 ?
b11010 G
b11010 S
b110 @
b0 "
b0 >
18
1(
