dualSevenSeg.v
module dualSevenSeg(data1,data2,display2,display1);
//this module will print to two 7-segment display's at the same time.
input [3:0]data1;
input [3:0]data2;
output [7:0] display1;
output [7:0] display2;
reg [7:0]display1;
reg [7:0]display2;

always @* //right-most digit, display1
begin
    casex (data1[3:0])
        4'b0000 : display1 = 8'b11000000; //0
        4'b0001 : display1 = 8'b11111001; //1
        4'b0010 : display1 = 8'b10100100; //2
        4'b0011 : display1 = 8'b10110000; //3
        4'b0100 : display1 = 8'b10011001; //4
        4'b0101 : display1 = 8'b10010010; //5
        4'b0110 : display1 = 8'b10000010; //6
        4'b0111 : display1 = 8'b11111000; //7
        4'b1000 : display1 = 8'b10000000; //8
        4'b1001 : display1 = 8'b10010000; //9
    endcase
end
always @*
begin
    casex (data2[3:0])
        4'b0000 : display2 = 8'b11111111; //blank
        4'b0001 : display2 = 8'b11111001; //1
        4'b0010 : display2 = 8'b10100100; //2
        4'b0011 : display2 = 8'b10110000; //3
        4'b0100 : display2 = 8'b10011001; //4
        4'b0101 : display2 = 8'b10010010; //5
        4'b0110 : display2 = 8'b10000010; //6
        4'b0111 : display2 = 8'b11111000; //7
        4'b1000 : display2 = 8'b10000000; //8
        4'b1001 : display2 = 8'b10010000; //9
    endcase
end
endmodule

counted.v
module counted(count, left, right);
input [6:0]count;
output [3:0]right;
output [3:0]left;
reg [3:0]left;
reg [3:0]right;
always @*
begin
right = (count %10);
left = (count /10);
end
endmodule

monthDayCalc.v
module monthDayCalc(data,month,day1,day2,SmoW);
//input number of the day of the year, outputs the month and day
// day1 is leftmost 7-seg (Overflow bit) , day2 is rightmost 7-seg
input [6:0] data;
output [7:0] month;//count
output [3:0] day1;//mod1
output [3:0] day2;//mod2
reg [7:0] dayData;//should be 7:0 not six 8 bit total
reg [7:0] month;
reg [3:0] day1;
reg [3:0] day2;


input [9:8]SW;


always @* //sending out month 7-segment binary value
begin
if(SW[9] == 1'b1)//leap year
begin
   if(data>=7'd92)  
    month = 8'b10011001; //4 - April
   else if(data>=7'd61)  
    month = 8'b10110000; //3 - March
   else if(data>=7'd32)
    month = 8'b10100100; //2 - February
   else
    month = 8'b11111001; //1 - January
end
else 
begin
   if(data>=7'd91)  
    month = 8'b10011001; //4 - April
   else if(data>=7'd60)  
    month = 8'b10110000; //3 - March
   else if(data>=7'd32)
    month = 8'b10100100; //2 - February
   else
    month = 8'b11111001; //1 - January
end
end

always @* //Get the date of the month
begin
if(SW[9] == 1'b1)
begin
   if(data>=7'd92)  
    dayData = (data % 7'd91); //4 - Aprl
   else if(data>=7'd61)  
    dayData = (data % 7'd60); //3 - March
   else if(data>=7'd32)
    dayData = (data % 7'd31); //2 - February
   else
    dayData = data;         //1 - January
end
else
begin
   if(data>=7'd91)  
    dayData = (data % 7'd90); //4 - Aprl
   else if(data>=7'd60)  
    dayData = (data % 7'd59); //3 - March
   else if(data>=7'd32)
    dayData = (data % 7'd31); //2 - February
   else
    dayData = data;         //1 - January
end
end

always @*
begin
    day2 = (dayData%10); //rightmost bit
    day1 = (dayData/10); //overflow left bit
end


endmodule

clock_divider.v
module clock_divider #(parameter clock_divisor1 = 5, parameter clock_divisor2 = 1_000_000) (clk, /*reset_n,*/clock_out, KEY);
//parameter clock_divisor = 5_000_000; //move to top in test pass 1
input [1:0]KEY;
input clk;
//input [0]reset_n;
//input [0]clock_divider; //TB = 1 TOP = 5_000_000
output [22:0]clock_out;
reg [22:0]clock_out = 0;
reg [23:0]counter = 0;


//(clock_divider #(clock_divisor = 1); //look up parameter verilog
always @(posedge clk or negedge clk)
begin
    /*if(KEY[0] == 1'b0)
    begin
        counter = 0;
        clock_out = 0;
    end*/
    if(KEY[1] == 1'b1)
    begin
        if(counter == clock_divisor1 - 1)
        begin
            counter <= 0;
            clock_out <= ~clock_out;
        end
        else
            counter <= counter + 1;
    end
    else
    begin
        if(counter == clock_divisor2 - 1)
        begin
            counter <= 0;
            clock_out <= ~clock_out;
        end
        else
            counter <= counter + 1;
    end
end


endmodule
/*
reg [6:0]count;
reg [3:0]mod10_counter1;
reg [3:0]mod10_counter2;
always @(posedge clk or negedge reset_n)
begin
if(reset_n == 0)
begin
mod10_counter1 <= 1; // start at 1
count <= 1; //count 1 - 99
end
else if (mod10_counter1 != 9)
begin
mod10_counter <= mod10_counter + 1;
count <= count + 1;
end
else if(count == 99)
mod10_counter1 <= 0;
else
begin
mod10_counter <= 0;
count <= count + 1;
end
end

always @(posedge clk or negedge reset_n)
begin
if(reset_n == 0)
mod10_counter2 <= 0;
else if(mod10_counter1 == 9)
begin
if (mod10_counter2 != 9)
mod10_counter2 <= mod10_counter2 + 1;
else
mod10_counter2 <= 0;
end
end


endmodule

module top(ADC_CLK_10)
input ADC_CLK_10;
*/

top.v
module top(KEY, HEX0, HEX1, HEX2, HEX3, HEX4, HEX5, ADC_CLK_10, LEDR, SW);
//clock input
input ADC_CLK_10;

//set input for KEY buttons
input [1:0] KEY; 
input [9:8] SW;
//Outputs need wires here because through the 3 blocks each hex holds 3 different values
output [7:0] HEX0; //Day2
output [7:0] HEX1; //Day1
output [7:0] HEX2; //Month 
output [7:0] HEX3; //Blank
output [7:0] HEX4; //Digit 2
output [7:0] HEX5; //Digit 1
output [1:0] LEDR;

assign HEX3[7:0] = 8'b11111111; // Make HEX3 blank
//count      reg [6:0]numTotal; //This is the number that is currently being displayed, like 99
wire[3:0]day1; //This is the HEX1 number representation
wire[3:0]day2; //This is the HEX0 number representation
wire[3:0]right;
wire[3:0]left;
wire [7:0]monthSeg; //7-seg display binary represntation for the month, HEX2
reg [1:0]LEDR = 2'b01;

//Latch the button
reg reset_n;
always @(negedge KEY[0])
begin
reset_n <= ~reset_n;
LEDR[0] = reset_n;
end


wire [22:0]clk_out;
clock_divider clock_divide(.clk(ADC_CLK_10),.clock_out(clk_out), .KEY(KEY[1:0]));

//Start Clock setup
reg [6:0]count;
reg [3:0]mod10_counter1;
reg [3:0]mod10_counter2;
//Day1
always @(posedge clk_out or negedge reset_n)
begin
if(reset_n == 0)
begin
mod10_counter1 <= 1; // start at 1
count <= 1; //count 1 - 99
end
else 
begin
LEDR[1] <= ~LEDR[1];
if(count == 99)
begin
mod10_counter1 <= 1;
count <= 1;
end
else 
if (mod10_counter1 != 9)
begin
mod10_counter1 <= mod10_counter1 + 1;
count <= count + 1;
end
else
begin
mod10_counter1 <= 0;
count <= count + 1;
end
end
end
//Day2
always @(posedge clk_out or negedge reset_n)
begin
if(reset_n == 0)
mod10_counter2 <= 0;
else if(mod10_counter1 == 9)
begin
if (/*mod10_counter2*/count != 100)
mod10_counter2 <= mod10_counter2 + 1;
else
begin
mod10_counter2 <= 0;
//count = 1;
end
end
end
// end clock setup



//This is kinda how were going to want to use monthDayCalc.v, but definetely change it to make it work for you

monthDayCalc monthDayCalc(.data(count),.month(HEX2),.day1(day1),.day2(day2),.SW(SW[9:8]));
dualSevenSeg dualSevenSegMD(.data1(day2),.data2(day1),.display2(HEX1),.display1(HEX0));
counted counted(.count(count),.left(left),.right(right));
dualSevenSeg dualSevenSegCNT(.data1(right),.data2(left),.display2(HEX5),.display1(HEX4));



endmodule

tb_project2.v
/* USE:
 ~from directory project2digitallogic/
 ~iverilog tb_project2.v top.v monthDayCalc.v dualSevenSeg.v clock_divider.v counted.v
 ~vvp a.out > out.txt
 */
`timescale 1 ms / 100 ps

module tb();

reg ADC_CLK_10;
reg  [9:8] SW;
reg  [1:0] KEY; //Buttons
wire [7:0] HEX0; //Day2
wire [7:0] HEX1; //Day1
wire [7:0] HEX2; //Month
wire [7:0] HEX3; //should always be blank
wire [7:0] HEX4; //Digit 1
wire [7:0] HEX5; //Digit 2
wire [1:0] LEDR;

reg [3:0] day1digit;
reg [3:0] day2digit;
reg [3:0] monthDigit;
reg [3:0] unusedMonthDig;
reg [3:0] digit1digit;
reg [3:0] digit2digit;

always #5 ADC_CLK_10 = ~ADC_CLK_10;

top DUT(
  .KEY(KEY),
  .HEX0(HEX0),
  .HEX1(HEX1),
  .HEX2(HEX2),
  .HEX3(HEX3),
  .HEX4(HEX4),
  .HEX5(HEX5),
  .ADC_CLK_10(ADC_CLK_10),
  .LEDR(LEDR),
  .SW(SW)  
);

initial
begin
    $dumpfile("out.vcd");
	$dumpvars;
    $display($time, " << Starting Simulation >>");
    ADC_CLK_10 = 1'b0;
    SW[9:8] = 2'b00;
    KEY[1:0] = 2'b11;
    $display($time, " SW[9] low: %b, no buttons KEY[1:0]= %b",SW[9],KEY[1:0]);
    #1000
    KEY[1:0] = 2'b10;
    #1000
    $display($time, " Pressing reset to begin, KEY[0] = %b, HEX3 Cleared: %b",KEY[0],HEX3[7:0]);
    repeat(100) begin
        if($time<3) KEY[1:0] = 2'b11;
        #1000
        $display($time, " Left Digit: HEX5 = %b, Right Digit: HEX4 = %b", HEX5[7:0], HEX4[7:0]);
        $display($time, " Left Day: HEX1 = %b, Right Day: HEX0 = %b, Month: HEX2 = %b",HEX1[7:0],HEX0[7:0],HEX2[7:0]);
        $display($time," Converted to digits: %d %d - %d %d - %d %d",
                   digit2digit[3:0],digit1digit[3:0],unusedMonthDig[3:0], monthDigit[3:0],day1digit[3:0],day2digit[3:0]);
    end
    
    $display($time, " Ending Simulation, by Connor Peskin");
	$finish;
end

initial
begin
      $monitor($time, " Buttons(KEY): %b, Day2(HEX0): %b, Day1(HEX1): %b, UnusedMonth(HEX3): %b, Month(HEX2): %b, Digit1(HEX4): %b, Digit2(HEX5): %b, Clk: %b",
                              KEY[1:0],      HEX0[7:0],      HEX1[7:0],               HEX3[7:0], HEX2[7:0],        HEX4[7:0],        HEX5[7:0], ADC_CLK_10);
end


always @* 
begin
    casex(HEX1[7:0])
        8'b11000000 : day1digit = 4'b0000; //0
        8'b11111001 : day1digit = 4'b0001; //1
        8'b10100100 : day1digit = 4'b0010; //2
        8'b10110000 : day1digit = 4'b0011; //3
        8'b10011001 : day1digit = 4'b0100; //4
        8'b10010010 : day1digit = 4'b0101; //5
        8'b10000010 : day1digit = 4'b0110; //6
        8'b11111000 : day1digit = 4'b0111; //7
        8'b10000000 : day1digit = 4'b1000; //8
        8'b10010000 : day1digit = 4'b1001; //9
    endcase
    casex(HEX0[7:0])
        8'b11000000 : day2digit = 4'b0000; //0
        8'b11111001 : day2digit = 4'b0001; //1
        8'b10100100 : day2digit = 4'b0010; //2
        8'b10110000 : day2digit = 4'b0011; //3
        8'b10011001 : day2digit = 4'b0100; //4
        8'b10010010 : day2digit = 4'b0101; //5
        8'b10000010 : day2digit = 4'b0110; //6
        8'b11111000 : day2digit = 4'b0111; //7
        8'b10000000 : day2digit = 4'b1000; //8
        8'b10010000 : day2digit = 4'b1001; //9
    endcase
    casex(HEX2[7:0])
        8'b11000000 : monthDigit = 4'b0000; //0
        8'b11111001 : monthDigit = 4'b0001; //1
        8'b10100100 : monthDigit = 4'b0010; //2
        8'b10110000 : monthDigit = 4'b0011; //3
        8'b10011001 : monthDigit = 4'b0100; //4
        8'b10010010 : monthDigit = 4'b0101; //5
        8'b10000010 : monthDigit = 4'b0110; //6
        8'b11111000 : monthDigit = 4'b0111; //7
        8'b10000000 : monthDigit = 4'b1000; //8
        8'b10010000 : monthDigit = 4'b1001; //9
    endcase
    casex(HEX3[7:0])
        8'b11000000 : unusedMonthDig = 4'b0000; //0
        8'b11111001 : unusedMonthDig = 4'b0001; //1
        8'b10100100 : unusedMonthDig = 4'b0010; //2
        8'b10110000 : unusedMonthDig = 4'b0011; //3
        8'b10011001 : unusedMonthDig = 4'b0100; //4
        8'b10010010 : unusedMonthDig = 4'b0101; //5
        8'b10000010 : unusedMonthDig = 4'b0110; //6
        8'b11111000 : unusedMonthDig = 4'b0111; //7
        8'b10000000 : unusedMonthDig = 4'b1000; //8
        8'b10010000 : unusedMonthDig = 4'b1001; //9
        8'b11111111 : unusedMonthDig = 4'b0000; //0
    endcase
    casex(HEX4[7:0])
        8'b11000000 : digit1digit = 4'b0000; //0
        8'b11111001 : digit1digit = 4'b0001; //1
        8'b10100100 : digit1digit = 4'b0010; //2
        8'b10110000 : digit1digit = 4'b0011; //3
        8'b10011001 : digit1digit = 4'b0100; //4
        8'b10010010 : digit1digit = 4'b0101; //5
        8'b10000010 : digit1digit = 4'b0110; //6
        8'b11111000 : digit1digit = 4'b0111; //7
        8'b10000000 : digit1digit = 4'b1000; //8
        8'b10010000 : digit1digit = 4'b1001; //9
    endcase
    casex(HEX5[7:0])
        8'b11000000 : digit2digit = 4'b0000; //0
        8'b11111001 : digit2digit = 4'b0001; //1
        8'b10100100 : digit2digit = 4'b0010; //2
        8'b10110000 : digit2digit = 4'b0011; //3
        8'b10011001 : digit2digit = 4'b0100; //4
        8'b10010010 : digit2digit = 4'b0101; //5
        8'b10000010 : digit2digit = 4'b0110; //6
        8'b11111000 : digit2digit = 4'b0111; //7
        8'b10000000 : digit2digit = 4'b1000; //8
        8'b10010000 : digit2digit = 4'b1001; //9
    endcase
end



endmodule

out.vcd
$date
	Mon Nov 04 16:03:46 2019
$end
$version
	Icarus Verilog
$end
$timescale
	100ps
$end
$scope module tb $end
$var wire 8 ! HEX3 [7:0] $end
$var wire 2 " LEDR [1:0] $end
$var wire 8 # HEX5 [7:0] $end
$var wire 8 $ HEX4 [7:0] $end
$var wire 8 % HEX2 [7:0] $end
$var wire 8 & HEX1 [7:0] $end
$var wire 8 ' HEX0 [7:0] $end
$var reg 1 ( ADC_CLK_10 $end
$var reg 2 ) KEY [1:0] $end
$var reg 2 * SW [9:8] $end
$var reg 4 + day1digit [3:0] $end
$var reg 4 , day2digit [3:0] $end
$var reg 4 - digit1digit [3:0] $end
$var reg 4 . digit2digit [3:0] $end
$var reg 4 / monthDigit [3:0] $end
$var reg 4 0 unusedMonthDig [3:0] $end
$scope module DUT $end
$var wire 1 ( ADC_CLK_10 $end
$var wire 8 1 HEX3 [7:0] $end
$var wire 2 2 KEY [1:0] $end
$var wire 2 3 SW [9:8] $end
$var wire 4 4 right [3:0] $end
$var wire 4 5 left [3:0] $end
$var wire 4 6 day2 [3:0] $end
$var wire 4 7 day1 [3:0] $end
$var wire 23 8 clk_out [22:0] $end
$var wire 8 9 HEX5 [7:0] $end
$var wire 8 : HEX4 [7:0] $end
$var wire 8 ; HEX2 [7:0] $end
$var wire 8 < HEX1 [7:0] $end
$var wire 8 = HEX0 [7:0] $end
$var reg 2 > LEDR [1:0] $end
$var reg 7 ? count [6:0] $end
$var reg 4 @ mod10_counter1 [3:0] $end
$var reg 4 A mod10_counter2 [3:0] $end
$var reg 1 B reset_n $end
$scope module clock_divide $end
$var wire 2 C KEY [1:0] $end
$var wire 1 ( clk $end
$var reg 23 D clock_out [22:0] $end
$var reg 24 E counter [23:0] $end
$upscope $end
$scope module counted $end
$var wire 7 F count [6:0] $end
$var reg 4 G left [3:0] $end
$var reg 4 H right [3:0] $end
$upscope $end
$scope module dualSevenSegCNT $end
$var wire 4 I data1 [3:0] $end
$var wire 4 J data2 [3:0] $end
$var reg 8 K display1 [7:0] $end
$var reg 8 L display2 [7:0] $end
$upscope $end
$scope module dualSevenSegMD $end
$var wire 4 M data2 [3:0] $end
$var wire 4 N data1 [3:0] $end
$var reg 8 O display1 [7:0] $end
$var reg 8 P display2 [7:0] $end
$upscope $end
$scope module monthDayCalc $end
$var wire 2 Q SW [9:8] $end
$var wire 7 R data [6:0] $end
$var reg 4 S day1 [3:0] $end
$var reg 4 T day2 [3:0] $end
$var reg 8 U dayData [7:0] $end
$var reg 8 V month [7:0] $end
$upscope $end
$upscope $end
$upscope $end
$enddefinitions $end
#0
$dumpvars
b11111001 V
b0xxxxxxx U
bx T
bx S
bx R
b0 Q
bx P
bx O
bx N
bx M
bx L
bx K
bx J
bx I
bx H
bx G
bx F
b1 E
b0 D
b11 C
0B
bx A
bx @
bx ?
b1 >
bx =
bx <
b11111001 ;
bx :
bx 9
b0 8
bx 7
bx 6
bx 5
bx 4
b0 3
b11 2
b11111111 1
b0 0
b1 /
b0 .
b0 -
b0 ,
b0 +
b0 *
b11 )
0(
bx '
bx &
b11111001 %
bx $
bx #
b1 "
b11111111 !
$end
#50000000
b10 E
1(
#100000000
b11 E
0(
#150000000
b100 E
1(
#200000000
b1 -
b1 ,
b11111111 &
b11111111 <
b11111111 P
b11111001 '
b11111001 =
b11111001 O
b11111111 #
b11111111 9
b11111111 L
b11111001 $
b11111001 :
b11111001 K
b0 7
b0 M
b0 S
b1 6
b1 N
b1 T
b0 5
b0 G
b0 J
b1 4
b1 H
b1 I
b1 U
b1 ?
b1 F
b1 R
b1 @
b0 A
b11111111111111111111111 8
b11111111111111111111111 D
b0 E
0(
#250000000
b1 E
1(
#300000000
b10 E
0(
#350000000
b11 E
1(
#400000000
b100 E
0(
#450000000
b0 8
b0 D
b0 E
1(
#500000000
b1 E
0(
#550000000
b10 E
1(
#600000000
b11 E
0(
#650000000
b100 E
1(
#700000000
b11111111111111111111111 8
b11111111111111111111111 D
b0 E
0(
#750000000
b1 E
1(
#800000000
b10 E
0(
#850000000
b11 E
1(
#900000000
b100 E
0(
#950000000
b0 8
b0 D
b0 E
1(
#1000000000
b1 E
0(
#1050000000
b10 E
1(
#1100000000
b11 E
0(
#1150000000
b100 E
1(
#1200000000
b11111111111111111111111 8
b11111111111111111111111 D
b0 E
0(
#1250000000
b1 E
1(
#1300000000
b10 E
0(
#1350000000
b11 E
1(
#1400000000
b100 E
0(
#1450000000
b0 8
b0 D
b0 E
1(
#1500000000
b1 E
0(
#1550000000
b10 E
1(
#1600000000
b11 E
0(
#1650000000
b100 E
1(
#1700000000
b11111111111111111111111 8
b11111111111111111111111 D
b0 E
0(
#1750000000
b1 E
1(
#1800000000
b10 E
0(
#1850000000
b11 E
1(
#1900000000
b100 E
0(
#1950000000
b0 8
b0 D
b0 E
1(
#2000000000
b1 E
0(
#2050000000
b10 E
1(
#2100000000
b11 E
0(
#2150000000
b100 E
1(
#2200000000
b11111111111111111111111 8
b11111111111111111111111 D
b0 E
0(
#2250000000
b1 E
1(
#2300000000
b10 E
0(
#2350000000
b11 E
1(
#2400000000
b100 E
0(
#2450000000
b0 8
b0 D
b0 E
1(
#2500000000
b1 E
0(
#2550000000
b10 E
1(
#2600000000
b11 E
0(
#2650000000
b100 E
1(
#2700000000
b11111111111111111111111 8
b11111111111111111111111 D
b0 E
0(
#2750000000
b1 E
1(
#2800000000
b10 E
0(
#2850000000
b11 E
1(
#2900000000
b100 E
0(
#2950000000
b0 8
b0 D
b0 E
1(
#3000000000
b1 E
0(
#3050000000
b10 E
1(
#3100000000
b11 E
0(
#3150000000
b100 E
1(
#3200000000
b11111111111111111111111 8
b11111111111111111111111 D
b0 E
0(
#3250000000
b1 E
1(
#3300000000
b10 E
0(
#3350000000
b11 E
1(
#3400000000
b100 E
0(
#3450000000
b0 8
b0 D
b0 E
1(
#3500000000
b1 E
0(
#3550000000
b10 E
1(
#3600000000
b11 E
0(
#3650000000
b100 E
1(
#3700000000
b11111111111111111111111 8
b11111111111111111111111 D
b0 E
0(
#3750000000
b1 E
1(
#3800000000
b10 E
0(
#3850000000
b11 E
1(
#3900000000
b100 E
0(
#3950000000
b0 8
b0 D
b0 E
1(
#4000000000
b1 E
0(
#4050000000
b10 E
1(
#4100000000
b11 E
0(
#4150000000
b100 E
1(
#4200000000
b11111111111111111111111 8
b11111111111111111111111 D
b0 E
0(
#4250000000
b1 E
1(
#4300000000
b10 E
0(
#4350000000
b11 E
1(
#4400000000
b100 E
0(
#4450000000
b0 8
b0 D
b0 E
1(
#4500000000
b1 E
0(
#4550000000
b10 E
1(
#4600000000
b11 E
0(
#4650000000
b100 E
1(
#4700000000
b11111111111111111111111 8
b11111111111111111111111 D
b0 E
0(
#4750000000
b1 E
1(
#4800000000
b10 E
0(
#4850000000
b11 E
1(
#4900000000
b100 E
0(
#4950000000
b0 8
b0 D
b0 E
1(
#5000000000
b1 E
0(
#5050000000
b10 E
1(
#5100000000
b11 E
0(
#5150000000
b100 E
1(
#5200000000
b11111111111111111111111 8
b11111111111111111111111 D
b0 E
0(
#5250000000
b1 E
1(
#5300000000
b10 E
0(
#5350000000
b11 E
1(
#5400000000
b100 E
0(
#5450000000
b0 8
b0 D
b0 E
1(
#5500000000
b1 E
0(
#5550000000
b10 E
1(
#5600000000
b11 E
0(
#5650000000
b100 E
1(
#5700000000
b11111111111111111111111 8
b11111111111111111111111 D
b0 E
0(
#5750000000
b1 E
1(
#5800000000
b10 E
0(
#5850000000
b11 E
1(
#5900000000
b100 E
0(
#5950000000
b0 8
b0 D
b0 E
1(
#6000000000
b1 E
0(
#6050000000
b10 E
1(
#6100000000
b11 E
0(
#6150000000
b100 E
1(
#6200000000
b11111111111111111111111 8
b11111111111111111111111 D
b0 E
0(
#6250000000
b1 E
1(
#6300000000
b10 E
0(
#6350000000
b11 E
1(
#6400000000
b100 E
0(
#6450000000
b0 8
b0 D
b0 E
1(
#6500000000
b1 E
0(
#6550000000
b10 E
1(
#6600000000
b11 E
0(
#6650000000
b100 E
1(
#6700000000
b11111111111111111111111 8
b11111111111111111111111 D
b0 E
0(
#6750000000
b1 E
1(
#6800000000
b10 E
0(
#6850000000
b11 E
1(
#6900000000
b100 E
0(
#6950000000
b0 8
b0 D
b0 E
1(
#7000000000
b1 E
0(
#7050000000
b10 E
1(
#7100000000
b11 E
0(
#7150000000
b100 E
1(
#7200000000
b11111111111111111111111 8
b11111111111111111111111 D
b0 E
0(
#7250000000
b1 E
1(
#7300000000
b10 E
0(
#7350000000
b11 E
1(
#7400000000
b100 E
0(
#7450000000
b0 8
b0 D
b0 E
1(
#7500000000
b1 E
0(
#7550000000
b10 E
1(
#7600000000
b11 E
0(
#7650000000
b100 E
1(
#7700000000
b11111111111111111111111 8
b11111111111111111111111 D
b0 E
0(
#7750000000
b1 E
1(
#7800000000
b10 E
0(
#7850000000
b11 E
1(
#7900000000
b100 E
0(
#7950000000
b0 8
b0 D
b0 E
1(
#8000000000
b1 E
0(
#8050000000
b10 E
1(
#8100000000
b11 E
0(
#8150000000
b100 E
1(
#8200000000
b11111111111111111111111 8
b11111111111111111111111 D
b0 E
0(
#8250000000
b1 E
1(
#8300000000
b10 E
0(
#8350000000
b11 E
1(
#8400000000
b100 E
0(
#8450000000
b0 8
b0 D
b0 E
1(
#8500000000
b1 E
0(
#8550000000
b10 E
1(
#8600000000
b11 E
0(
#8650000000
b100 E
1(
#8700000000
b11111111111111111111111 8
b11111111111111111111111 D
b0 E
0(
#8750000000
b1 E
1(
#8800000000
b10 E
0(
#8850000000
b11 E
1(
#8900000000
b100 E
0(
#8950000000
b0 8
b0 D
b0 E
1(
#9000000000
b1 E
0(
#9050000000
b10 E
1(
#9100000000
b11 E
0(
#9150000000
b100 E
1(
#9200000000
b11111111111111111111111 8
b11111111111111111111111 D
b0 E
0(
#9250000000
b1 E
1(
#9300000000
b10 E
0(
#9350000000
b11 E
1(
#9400000000
b100 E
0(
#9450000000
b0 8
b0 D
b0 E
1(
#9500000000
b1 E
0(
#9550000000
b10 E
1(
#9600000000
b11 E
0(
#9650000000
b100 E
1(
#9700000000
b11111111111111111111111 8
b11111111111111111111111 D
b0 E
0(
#9750000000
b1 E
1(
#9800000000
b10 E
0(
#9850000000
b11 E
1(
#9900000000
b100 E
0(
#9950000000
b0 8
b0 D
b0 E
1(
#10000000000
1B
b1 E
b0 "
b0 >
0(
b10 )
b10 2
b10 C
#10050000000
b10 E
1(
#10100000000
b11 E
0(
#10150000000
b100 E
1(
#10200000000
b10 -
b10 ,
b10100100 '
b10100100 =
b10100100 O
b10100100 $
b10100100 :
b10100100 K
b10 6
b10 N
b10 T
b10 4
b10 H
b10 I
b10 U
b10 ?
b10 F
b10 R
b10 @
b10 "
b10 >
b11111111111111111111111 8
b11111111111111111111111 D
b0 E
0(
#10250000000
b1 E
1(
#10300000000
b10 E
0(
#10350000000
b11 E
1(
#10400000000
b100 E
0(
#10450000000
b0 8
b0 D
b0 E
1(
#10500000000
b1 E
0(
#10550000000
b10 E
1(
#10600000000
b11 E
0(
#10650000000
b100 E
1(
#10700000000
b11 -
b11 ,
b10110000 '
b10110000 =
b10110000 O
b10110000 $
b10110000 :
b10110000 K
b11 6
b11 N
b11 T
b11 4
b11 H
b11 I
b11 U
b11 ?
b11 F
b11 R
b11 @
b0 "
b0 >
b11111111111111111111111 8
b11111111111111111111111 D
b0 E
0(
#10750000000
b1 E
1(
#10800000000
b10 E
0(
#10850000000
b11 E
1(
#10900000000
b100 E
0(
#10950000000
b0 8
b0 D
b0 E
1(
#11000000000
b1 E
0(
#11050000000
b10 E
1(
#11100000000
b11 E
0(
#11150000000
b100 E
1(
#11200000000
b100 -
b100 ,
b10011001 '
b10011001 =
b10011001 O
b10011001 $
b10011001 :
b10011001 K
b100 6
b100 N
b100 T
b100 4
b100 H
b100 I
b100 U
b100 ?
b100 F
b100 R
b100 @
b10 "
b10 >
b11111111111111111111111 8
b11111111111111111111111 D
b0 E
0(
#11250000000
b1 E
1(
#11300000000
b10 E
0(
#11350000000
b11 E
1(
#11400000000
b100 E
0(
#11450000000
b0 8
b0 D
b0 E
1(
#11500000000
b1 E
0(
#11550000000
b10 E
1(
#11600000000
b11 E
0(
#11650000000
b100 E
1(
#11700000000
b101 -
b101 ,
b10010010 '
b10010010 =
b10010010 O
b10010010 $
b10010010 :
b10010010 K
b101 6
b101 N
b101 T
b101 4
b101 H
b101 I
b101 U
b101 ?
b101 F
b101 R
b101 @
b0 "
b0 >
b11111111111111111111111 8
b11111111111111111111111 D
b0 E
0(
#11750000000
b1 E
1(
#11800000000
b10 E
0(
#11850000000
b11 E
1(
#11900000000
b100 E
0(
#11950000000
b0 8
b0 D
b0 E
1(
#12000000000
b1 E
0(
#12050000000
b10 E
1(
#12100000000
b11 E
0(
#12150000000
b100 E
1(
#12200000000
b110 -
b110 ,
b10000010 '
b10000010 =
b10000010 O
b10000010 $
b10000010 :
b10000010 K
b110 6
b110 N
b110 T
b110 4
b110 H
b110 I
b110 U
b110 ?
b110 F
b110 R
b110 @
b10 "
b10 >
b11111111111111111111111 8
b11111111111111111111111 D
b0 E
0(
#12250000000
b1 E
1(
#12300000000
b10 E
0(
#12350000000
b11 E
1(
#12400000000
b100 E
0(
#12450000000
b0 8
b0 D
b0 E
1(
#12500000000
b1 E
0(
#12550000000
b10 E
1(
#12600000000
b11 E
0(
#12650000000
b100 E
1(
#12700000000
b111 -
b111 ,
b11111000 '
b11111000 =
b11111000 O
b11111000 $
b11111000 :
b11111000 K
b111 6
b111 N
b111 T
b111 4
b111 H
b111 I
b111 U
b111 ?
b111 F
b111 R
b111 @
b0 "
b0 >
b11111111111111111111111 8
b11111111111111111111111 D
b0 E
0(
#12750000000
b1 E
1(
#12800000000
b10 E
0(
#12850000000
b11 E
1(
#12900000000
b100 E
0(
#12950000000
b0 8
b0 D
b0 E
1(
#13000000000
b1 E
0(
#13050000000
b10 E
1(
#13100000000
b11 E
0(
#13150000000
b100 E
1(
#13200000000
b1000 -
b1000 ,
b10000000 '
b10000000 =
b10000000 O
b10000000 $
b10000000 :
b10000000 K
b1000 6
b1000 N
b1000 T
b1000 4
b1000 H
b1000 I
b1000 U
b1000 ?
b1000 F
b1000 R
b1000 @
b10 "
b10 >
b11111111111111111111111 8
b11111111111111111111111 D
b0 E
0(
#13250000000
b1 E
1(
#13300000000
b10 E
0(
#13350000000
b11 E
1(
#13400000000
b100 E
0(
#13450000000
b0 8
b0 D
b0 E
1(
#13500000000
b1 E
0(
#13550000000
b10 E
1(
#13600000000
b11 E
0(
#13650000000
b100 E
1(
#13700000000
b1001 -
b1001 ,
b10010000 '
b10010000 =
b10010000 O
b10010000 $
b10010000 :
b10010000 K
b1001 6
b1001 N
b1001 T
b1001 4
b1001 H
b1001 I
b1001 U
b1001 ?
b1001 F
b1001 R
b1001 @
b0 "
b0 >
b11111111111111111111111 8
b11111111111111111111111 D
b0 E
0(
#13750000000
b1 E
1(
#13800000000
b10 E
0(
#13850000000
b11 E
1(
#13900000000
b100 E
0(
#13950000000
b0 8
b0 D
b0 E
1(
#14000000000
b1 E
0(
#14050000000
b10 E
1(
#14100000000
b11 E
0(
#14150000000
b100 E
1(
#14200000000
b1 .
b0 -
b0 ,
b1 +
b11111001 &
b11111001 <
b11111001 P
b11000000 '
b11000000 =
b11000000 O
b11111001 #
b11111001 9
b11111001 L
b11000000 $
b11000000 :
b11000000 K
b1 7
b1 M
b1 S
b0 6
b0 N
b0 T
b1 5
b1 G
b1 J
b0 4
b0 H
b0 I
b1010 U
b1010 ?
b1010 F
b1010 R
b0 @
b10 "
b10 >
b1 A
b11111111111111111111111 8
b11111111111111111111111 D
b0 E
0(
#14250000000
b1 E
1(
#14300000000
b10 E
0(
#14350000000
b11 E
1(
#14400000000
b100 E
0(
#14450000000
b0 8
b0 D
b0 E
1(
#14500000000
b1 E
0(
#14550000000
b10 E
1(
#14600000000
b11 E
0(
#14650000000
b100 E
1(
#14700000000
b1 -
b1 ,
b11111001 '
b11111001 =
b11111001 O
b11111001 $
b11111001 :
b11111001 K
b1 6
b1 N
b1 T
b1 4
b1 H
b1 I
b1011 U
b1011 ?
b1011 F
b1011 R
b1 @
b0 "
b0 >
b11111111111111111111111 8
b11111111111111111111111 D
b0 E
0(
#14750000000
b1 E
1(
#14800000000
b10 E
0(
#14850000000
b11 E
1(
#14900000000
b100 E
0(
#14950000000
b0 8
b0 D
b0 E
1(
#15000000000
b1 E
0(
#15050000000
b10 E
1(
#15100000000
b11 E
0(
#15150000000
b100 E
1(
